{
  "kind": "collectionType",
  "collectionName": "campaigns",
  "info": {
    "singularName": "campaign",
    "pluralName": "campaigns",
    "displayName": "Campaign",
    "description": ""
  },
  "options": {
    "draftAndPublish": true
  },
  "pluginOptions": {},
  "attributes": {
    "title": {
      "type": "string"
    },
    "description": {
      "type": "text"
    },
    "goal": {
      "type": "decimal"
    },
    "start_date": {
      "type": "date"
    },
    "end_date": {
      "type": "date"
    },
    "youtube_link": {
      "type": "string"
    },
    "image": {
      "allowedTypes": [
        "images",
        "files",
        "videos",
        "audios"
      ],
      "type": "media",
      "multiple": true
    }
  }
}
